{
    "version": "14.0.10.0",
    "description": "A cross-platform manager for Jexus web server, IIS, and IIS Express.",
    "homepage": "https://github.com/jexuswebserver/JexusManager",
    "license": "MIT",
    "architecture": {
        "64bit": {
            "url": "https://github.com/jexuswebserver/JexusManager/releases/download/v14.0.10.0/JexusManager_x64.msi",
            "hash": "c35c91f5f78faa9757e0f04a3e576e2c590bfd884e264368994477560c25b405"
        },
        "arm64": {
            "url": "https://github.com/jexuswebserver/JexusManager/releases/download/v14.0.10.0/JexusManager_arm64.msi",
            "hash": "8DB6E86002CC27250313B2D18BEC93227E6BFA61"
        }
    },
    "extract_dir": "PFiles\\LeXtudio\\Jexus Manager",
    "bin": "JexusManager.exe",
    "shortcuts": [
        [
            "JexusManager.exe",
            "Jexus Manager"
        ]
    ],
    "checkver": {
        "github": "https://github.com/jexuswebserver/JexusManager"
    },
    "autoupdate": {
        "architecture": {
            "64bit": {
                "url": "https://github.com/jexuswebserver/JexusManager/releases/download/v$version/JexusManager_x64.msi"
            },
            "arm64": {
                "url": "https://github.com/jexuswebserver/JexusManager/releases/download/v$version/JexusManager_arm64.msi"
            }
        }
    }
}
